README.md
setup.cfg
setup.py
Cryptolite.egg-info/PKG-INFO
Cryptolite.egg-info/SOURCES.txt
Cryptolite.egg-info/dependency_links.txt
Cryptolite.egg-info/top_level.txt
Cryptolite.egg-info/zip-safe
cryptolite/__init__.py
cryptolite/byte_array.py
cryptolite/generate.py
cryptolite/keys.py
tests/__init__.py
tests/test_byte_array.py
tests/test_generate.py
tests/test_keys.py